libuuu-1.5.243.dist-info/RECORD
libuuu-1.5.243.dist-info/WHEEL
libuuu-1.5.243.dist-info/top_level.txt
libuuu-1.5.243.dist-info/METADATA
libuuu-1.5.243.dist-info/licenses/LICENSE
libuuu/__init__.py
libuuu/__version__.py
libuuu/libuuu.py
libuuu/lib/darwin/x86_64/libuuu.dylib
