Metadata-Version: 2.4
Name: libuuu
Version: 1.5.243
Summary: A python wraper for libuuu.
Author: NXP
License: BSD-3-Clause
Project-URL: Homepage, https://github.com/nxp-imx/mfgtools/tree/master/wrapper
Keywords: NXP
Classifier: Development Status :: 2 - Pre-Alpha
Classifier: Intended Audience :: Developers
Classifier: License :: OSI Approved :: BSD License
Classifier: Natural Language :: English
Classifier: Programming Language :: Python :: 3
Classifier: Programming Language :: Python :: 3.9
Classifier: Programming Language :: Python :: 3.10
Classifier: Programming Language :: Python :: 3.11
Requires-Python: >=3.9
License-File: LICENSE
Dynamic: license-file
